Workbook

Sheet Resumen
A1: TransportesNova — Análisis Comparativo de Costos por Metodología
A2: Basado en el backlog real de Jira · 92 Historias de Usuario · 623 Story Points
A4: Métrica | B4: SCRUM | C4: KANBAN | D4: SCRUMBAN | E4: XP | F4: WSF
A5: Duración del Proyecto | B5: =SCRUM!B19&" meses" -> 10,5511932255581 meses | C5: =KANBAN!B20&" meses" -> 20 meses | D5: =SCRUMBAN!B22/2&" meses build" -> 12,5 meses build | E5: =XP!B19&" meses" -> 11 meses | F5: =('Water Scrum Fall'!B14+'Water Scrum Fall'!B25+'Water Scrum Fall'!B40)&" meses" -> 14,0511932255581 meses
A6: Total Story Points / Historias | B6: =SCRUM!B14&" SP" -> 623 SP | C6: =74&" tareas" -> 74 tareas | D6: =SCRUMBAN!B20&" SP" -> 623 SP | E6: =XP!B10&" SP" -> 623 SP | F6: ="623 SP + Docs" -> 623 SP + Docs
A7: Costo Total del Proyecto (Interno) | B7: =SCRUM!B24 -> 514250 | C7: =KANBAN!B25 -> 935000 | D7: =SCRUMBAN!B40 -> 423087.5 | E7: =XP!B32 -> 514250 | F7: ='Water Scrum Fall'!B64 -> 819168.28
A8: Ingreso Total del Proyecto (Venta) | B8: =SCRUM!B25 -> 1067925.8 | C8: =KANBAN!B24 -> 2400000 | D8: =SCRUMBAN!B39 -> 1057718.8 | E8: =XP!B27*XP!B19 -> 1320000 | F8: ='Water Scrum Fall'!B69 -> 1489396.9
A9: Margen Bruto | B9: =SCRUM!B26 -> 553675.83 | C9: =KANBAN!B26 -> 1465000 | D9: =SCRUMBAN!B43 -> 634631.25 | E9: =E8-E7 -> 805750 | F9: ='Water Scrum Fall'!B71 -> 670228.6
A10: Margen Bruto % (sobre venta) | B10: =SCRUM!B26/SCRUM!B25 -> 0.51845907 | C10: =KANBAN!B26/KANBAN!B24 -> 0.61041667 | D10: =SCRUMBAN!B43/SCRUMBAN!B39 -> 0.6 | E10: =E9/E8 -> 0.61041667 | F10: =F9/F8 -> 0.45
A11: Costo por Unidad de Trabajo | B11: =SCRUM!B24/SCRUM!B14&" Q/SP" -> 825,441412520064 Q/SP | C11: =KANBAN!B25/KANBAN!B15&" Q/hist" -> 7923,72881355932 Q/hist | D11: Ver hoja SCRUMBAN | E11: =XP!B32/XP!B10&" Q/SP" -> 825,441412520064 Q/SP | F11: ="Precio fijo cerrado" -> Precio fijo cerrado
A12: Equipo Mensual (costo interno) | B12: =Equipo!E13 -> 46750 | C12: =Equipo!E13 -> 46750 | D12: =Equipo!E13 -> 46750 | E12: =Equipo!E13 -> 46750 | F12: =Equipo!E13 -> 46750
A14: NOTAS METODOLÓGICAS
A15: SCRUM: | B15: Iteraciones fijas (sprints). Mejor para proyectos con alcance definido y necesidad de entregas periódicas predecibles.
A16: KANBAN: | B16: Flujo continuo sin sprints. Mejor para proyectos con requerimientos cambiantes; duración mayor pero más flexible.
A17: SCRUMBAN: | B17: Híbrido: Build con disciplina de sprints + Run con flujo Kanban continuo. Ideal para equipos que entregan Y mantienen.
A18: XP: | B18: Enfoque en calidad: pair programming, TDD, integración continua. Mejor para proyectos donde la calidad del código es crítica.
A19: WATER-SCRUM-FALL: | B19: Híbrido tradicional+ágil: planificación cascada inicial + desarrollo Scrum + despliegue cascada final. Precio fijo cerrado. Ideal para empresas con procesos formales y gobierno corporativo.

Sheet SCRUM
A1: SCRUM — Estimación de Costos del Proyecto
A3: SUPUESTOS DE EQUIPO
A4: Costo Total del Equipo / Mes | B4: =Equipo!E12 -> 93500 | C4: Q/mes | D4: Vinculado desde hoja Equipo
A5: Costo Interno (50% FTE) / Mes | B5: =Equipo!E13 -> 46750 | C5: Q/mes | D5: Vinculado desde hoja Equipo
A7: SUPUESTOS DE METODOLOGÍA SCRUM
A8: Velocidad del Equipo | B8: 30 | C8: SP / sprint | D8: Story Points por sprint de 2 semanas
A9: Duración del Sprint | B9: 2 | C9: semanas
A10: Factor de Holgura (buffer) | B10: 1.1 | D10: 10% de margen sobre estimación base
A11: Precio de Venta por Sprint | B11: =B4/B9 -> 46750 | C11: Q / sprint | D11: Tarifa comercial acordada con cliente
A13: BACKLOG — STORY POINTS TOTALES
A14: TOTAL STORY POINTS DEL PROYECTO | B14: =Backlog!F150 -> 623 | C14: SP totales
A16: CÁLCULOS DEL PROYECTO
A17: Total Sprints (sin holgura) | B17: =B14/B8 -> 20.766667 | C17: sprints | D17: SP totales ÷ velocidad
A18: Total Sprints (con holgura) | B18: =B17*B10 -> 22.843333 | C18: sprints | D18: × factor 10 de holgura
A19: Duración Total del Proyecto | B19: =B18*B9/4.33 -> 10.551193 | C19: meses | D19: Semanas totales ÷ 4.33 semanas/mes
A20: Meses | B20: 11 | C20: Meses
A21: Costo Interno por Sprint | B21: =B5/(4.33/B9) -> 21593.533 | C21: Q/sprint | D21: Costo mensual interno ÷ sprints por mes
A22: mesis
A23: RESUMEN FINANCIERO
A24: Costo Total del Proyecto (Interno) | B24: =B20*B11 -> 514250 | C24: Q
A25: Ingreso Total del Proyecto (Venta) | B25: =B18*B11 -> 1067925.8 | C25: Q
A26: Margen Bruto | B26: =B25-B24 -> 553675.83 | C26: Q
A27: Margen Bruto % (sobre venta) | B27: =B26/B25 -> 0.51845907 | C27: % | D27: Ingreso menos Costo, dividido Ingreso
A28: Markup % (margen sobre costo) | B28: =B26/B24 -> 1.0766667 | C28: % | D28: Ingreso menos Costo, dividido Costo
A29: Costo por Story Point | B29: =B24/B14 -> 825.44141 | C29: Q/SP | D29: Costo total ÷ SP totales
A31: Leyenda: Amarillo = input/supuesto editable Azul = fórmula calculada Verde = vinculado desde otra hoja
A33: VELOCIDAD DEL EQUIPO DE TRABAJO
A34: Senior 1: | B34: 18–20 | C34: SP
A35: Senior 2: | B35: 18–20 | C35: SP
A36: Junior 1: | B36: 10–12 | C36: SP
A37: Junior 2: | B37: 10–12 | C37: SP

Sheet SCRUMBAN
A1: SCRUMBAN — Estimación de Costos del Proyecto
A3: SUPUESTOS DE EQUIPO
A4: Costo Total del Equipo / Mes | B4: =Equipo!E13 -> 46750 | C4: Q/mes | D4: Vinculado desde hoja Equipo
A5: Costo Interno (50% FTE) / Mes | B5: =Equipo!E13 -> 46750 | C5: Q/mes | D5: Costo asignado al proyecto (base para márgenes)
A7: SUPUESTOS SCRUMBAN — FASE BUILD (Sprints Scrum)
A8: Velocidad del Equipo | B8: 30 | C8: SP/sprint | D8: Story Points por sprint de 2 semanas
A9: Duración del Sprint | B9: 2 | C9: semanas
A10: Factor Holgura Build | B10: 1.2 | D10: 20% buffer para fase de desarrollo
A11: Capacidad BUILD (desarrollo activo) | B11: 0.7 | C11: =B11 -> 0.7 | D11: 70% del equipo en features nuevas
A12: Capacidad RUN (operación/mantenimiento) | B12: 0.3 | C12: =B12 -> 0.3 | D12: 30% del equipo en soporte continuo
A14: SUPUESTOS SCRUMBAN — FASE RUN (Kanban continuo)
A15: Lead Time promedio (fase Run) | B15: 10 | C15: días | D15: Días por historia en modo operativo
A16: WIP Limit (fase Run) | B16: 3 | C16: tareas
A17: Días laborales por mes | B17: 20 | C17: días/mes
A19: BACKLOG
A20: Total Story Points | B20: =Backlog!F150 -> 623 | C20: SP
A21: Sprints | B21: =B20/B8 -> 20.766667 | C21: sprints
A22: Sprints con holgura | B22: =ROUND(B21*B10,0) -> 25
A23: COSTOS BUILD Y COSTOS RUN
A24: Costo Build | B24: =B4*B11 -> 32725
A25: Costo Run | B25: =B4*B12 -> 14025
B26: =SUM(B24:B25) -> 46750
A27: MARGEN OBJETIVO
A28: Margen objetivo | B28: 0.6
A31: PRECIOS
A32: Precio Build | B32: =B24/(1-B28) -> 81812.5
A33: Precio Run | B33: =B25/(1-B28) -> 35062.5
A35: Precio Build por sprint | B35: =B32/B9 -> 40906.25
A38: INGRESOS Y COSTOS
A39: Ingreso Total | B39: =B33+(B22*B35) -> 1057718.8
A40: Costo Total | B40: =((B24)*(B22/B9))+(B25) -> 423087.5
A42: MARGEN BRUTO Y PORCENTAJE DE MARGEN
A43: Margen bruto | B43: =B39-B40 -> 634631.25
A44: Margen % | B44: =B43/B39 -> 0.6

Sheet KANBAN
A1: KANBAN — Estimación de Costos del Proyecto
A3: SUPUESTOS DE EQUIPO
A4: Costo Total del Equipo / Mes | B4: =Equipo!E12 -> 93500 | C4: Q/mes | D4: Vinculado desde hoja Equipo
A5: Costo Interno (50% FTE) / Mes | B5: =Equipo!E13 -> 46750 | C5: Q/mes | D5: Vinculado desde hoja Equipo
A7: SUPUESTOS DE METODOLOGÍA KANBAN
A8: Cycle Time promedio | B8: 7 | C8: días | D8: Días efectivos de trabajo por historia
A9: Lead Time promedio | B9: 10 | C9: días | D9: Días totales incluyendo cola/espera
A10: WIP Limit (tareas en paralelo) | B10: 3 | C10: tareas | D10: Límite de trabajo en progreso simultáneo
A11: Días laborales por mes | B11: 20 | C11: días/mes | D11: Días hábiles de trabajo mensual
A12: Precio de Venta / Mes | B12: 120000 | C12: Q/mes | D12: Tarifa mensual comercial cobrada al cliente
A14: VOLUMEN DE TRABAJO — BACKLOG
A15: Total Historias de Usuario (Backlog) | B15: =Backlog!A151 -> 118 | C15: historias | D15: Historias activas del backlog en Jira (10 épicas)
A17: CÁLCULOS DE FLUJO
A18: Total Días de Trabajo | B18: =B15*B9 -> 1180 | C18: días | D18: Historias × Lead Time
A19: Días Ajustados por WIP | B19: =B18/B10 -> 393.33333 | C19: días | D19: Lead Time total ÷ WIP Limit (paralelismo)
A20: Duración Total del Proyecto | B20: =CEILING(B19/B11,1) -> 20 | C20: meses | D20: Días ajustados ÷ días laborales/mes (redondeado arriba)
A21: Throughput (historias / mes) | B21: =B10*B11/B9 -> 6 | C21: hist/mes | D21: WIP × días/mes ÷ Lead Time
A23: RESUMEN FINANCIERO
A24: Ingreso Total del Proyecto (Venta) | B24: =B20*B12 -> 2400000 | C24: Q
A25: Costo Total del Proyecto (Interno) | B25: =B20*B5 -> 935000 | C25: Q
A26: Margen Bruto | B26: =B24-B25 -> 1465000 | C26: Q
A27: Margen Bruto % (sobre venta) | B27: =B26/B24 -> 0.61041667 | C27: %
A28: Markup % (margen sobre costo) | B28: =B26/B25 -> 1.5668449 | C28: %
A29: Costo por Historia de Usuario | B29: =B25/B15 -> 7923.7288 | C29: Q/hist

Sheet XP
A1: EXTREME PROGRAMMING (XP) — Estimación de Costos del Proyecto
A2: TransportesNova — Basado en metodología XP: enfoque en calidad del código, pair programming, pruebas continuas
A4: 1. BURN RATE — Costo Real Mensual del Equipo
A5: Fórmula: Costo real mensual = Σ (Costo persona × FTE)
A7: BURN RATE (Costo real mensual) | D7: =Equipo!E13 -> 46750
A9: 2. PARÁMETROS DEL PROYECTO
A10: Total Story Points del Proyecto | B10: =Backlog!F150 -> 623 | C10: SP | D10: Backlog real con 92 historias en 10 épicas
A11: Velocidad del Equipo | B11: 30 | C11: SP/sprint | D11: Story Points completados por sprint
A12: Duración del Sprint | B12: 2 | C12: semanas | D12: Iteración corta estilo XP
A13: Factor de Holgura (buffer) | B13: 46296 | D13: 10% de margen sobre estimación base
A15: 3. CÁLCULOS DEL PROYECTO
A16: Total Sprints (sin holgura) | B16: =B10/B11 -> 20.766667 | C16: sprints | D16: SP totales ÷ velocidad
A17: Total Sprints (con holgura) | B17: =B16+B16*0.1 -> 22.843333 | C17: sprints | D17: × factor de holgura, redondeado
A18: Duración Total del Proyecto | B18: =(B17*2)/4.33 -> 10.551193 | C18: meses | D18: Semanas totales ÷ 4.33 semanas/mes
B19: 11 | C19: Meses
A20: 4. PRECIO AL CLIENTE (Markup Libre — estilo PDF profesor)
A21: Considera: costo real del equipo + riesgo del proyecto + gastos administrativos
A22: Margen objetivo (%) | B22: 0.6 | C22: % | D22: Margen sobre venta (PDF: ~24%)
A23: Precio al cliente mensual | B23: =D7/(1-B22) -> 116875 | C23: Q/mes | D23: Costo real mensual / (1 - margen)
A25: 5. RESUMEN FINANCIERO MENSUAL (estilo PDF profesor)
A26: Costo real mensual (Burn Rate) | B26: =D7 -> 46750 | D26: Σ (Costo persona × FTE)
A27: Precio al cliente mensual | B27: 120000 | D27: Precio acordado con cliente
A28: Margen Bruto mensual | B28: =B27-B26 -> 73250 | D28: Margen Bruto = Precio − Costo Real
A29: Margen % mensual | B29: =(B28/B27)*100 -> 61.041667 | D29: Margen % = (Margen Bruto ÷ Precio) × 100
A31: 6. RESUMEN FINANCIERO — TOTAL DEL PROYECTO
A32: Costo Total del Proyecto | B32: =B26*B19 -> 514250 | D32: Burn Rate × Duración en meses
A33: Venta Proyecto | B33: =B27*B19 -> 1320000
A34: Ganancia Total | B34: =B33-B32 -> 805750

Sheet Water Scrum Fall
A1: WATER-SCRUM-FALL — Estimación de Costos del Proyecto
A2: Metodología híbrida: Water (cascada inicial) → Scrum (desarrollo ágil) → Fall (despliegue cascada). Contrato de precio fijo.
A4: FASE 1 — WATER (Planificación inicial - Cascada)
A5: Lógica de costo: Costo Mensual del Equipo Water × Duración en meses. Solo participan PO, Seniors y SM. Devs aún no están activos.
A7: Rol | B7: Salario (Q) | C7: FTE | D7: Costo Asignado (Q) | G7: Función en Water
A8: Product Owner | B8: 22000 | C8: 1 | D8: =B8*C8 -> 22000 | G8: Definir backlog detallado y validar requerimientos
A9: Senior - Cloud Engineer | B9: 15500 | C9: 1 | D9: =B9*C9 -> 15500 | G9: Diseño arquitectónico técnico del sistema
A10: Senior - DevOps | B10: 14000 | C10: 0.5 | D10: =B10*C10 -> 7000 | G10: Planificación de infraestructura y CI/CD
A11: SM/Facilitador | B11: 16500 | C11: 0.5 | D11: =B11*C11 -> 8250 | G11: Coordinación, contratos, plan de gestión
A12: COSTO MENSUAL EQUIPO WATER | D12: =SUM(D8:D11) -> 52750 | G12: Σ Salario × FTE de roles activos
A14: Duración fase Water | B14: 2 | C14: meses | G14: Análisis, diseño arquitectónico, contratos
A15: COSTO TOTAL FASE WATER | B15: =D12*B14 -> 105500 | G15: Fórmula: costo mensual × Duración
A18: FASE 2 — SCRUM (Desarrollo iterativo - Ágil)
A19: Lógica de costo: Reutilizamos cálculos de la hoja SCRUM. Equipo completo activo durante sprints.
A21: Costo Interno Mensual (Equipo completo) | B21: =SCRUM!B5 -> 46750 | C21: Q/mes | G21: Vinculado de hoja SCRUM (50% FTE)
A22: Story Points Totales | B22: =SCRUM!B14 -> 623 | C22: SP | G22: Vinculado de hoja SCRUM
A23: Velocidad del Equipo | B23: =SCRUM!B8 -> 30 | C23: SP/sprint | G23: Vinculado de hoja SCRUM
A24: Total Sprints (con holgura) | B24: =SCRUM!B18 -> 22.843333 | C24: sprints | G24: Vinculado de hoja SCRUM
A25: Duración fase Scrum | B25: =SCRUM!B19 -> 10.551193 | C25: meses | G25: Vinculado de hoja SCRUM
A27: COSTO TOTAL FASE SCRUM | B27: =B21*B25 -> 493268.28 | G27: Vinculado: Costo total del proyecto Scrum
A30: FASE 3 — FALL (Despliegue y cierre - Cascada)
A31: Lógica de costo: Costo mensual × duración. Equipo reducido: QA, Seniors, PO parcial. Devs salen del proyecto.
A33: Rol | B33: Salario (Q) | C33: FTE | D33: Costo Asignado (Q) | G33: Función en Fall
A34: QA Engineer | B34: 7500 | C34: 1 | D34: =B34*C34 -> 7500 | G34: Pruebas finales intensivas, UAT
A35: Senior - DevOps | B35: 14000 | C35: 1 | D35: =B35*C35 -> 14000 | G35: Despliegue a producción, infraestructura
A36: Senior - Cloud Engineer | B36: 15500 | C36: 1 | D36: =B36*C36 -> 15500 | G36: Configuración entorno productivo
A37: Product Owner | B37: 22000 | C37: 0.3 | D37: =B37*C37 -> 6600 | G37: Validación UAT y firma de aceptación
A38: COSTO MENSUAL EQUIPO FALL | D38: =SUM(D34:D37) -> 43600 | G38: Σ Salario × FTE de roles activos
A40: Duración fase Fall | B40: 1.5 | C40: meses | G40: QA final, UAT, despliegue, capacitación
A41: COSTO TOTAL FASE FALL | B41: =D38*B40 -> 65400 | G41: Fórmula: costo mensual × Duración
A44: COSTOS EXTRA WATER-SCRUM-FALL
A45: Documentación formal, auditorías, certificaciones, capacitación: requeridos por contrato de precio fijo y gobierno corporativo.
A47: Concepto | B47: Costo (Q) | C47: Fase | G47: Justificación
A48: Documentación formal extendida | B48: 20000 | C48: Water+Fall | G48: Planes, diagramas, manuales (PMBOK)
A49: Análisis de negocio profundo | B49: 15000 | C49: Water | G49: Requerimientos detallados pre-desarrollo
A50: Diseño arquitectónico formal | B50: 20000 | C50: Water | G50: Arquitectura completa antes de codear
A51: Auditoría externa de seguridad | B51: 30000 | C51: Fall | G51: Validación antes de producción
A52: UAT formal con cliente | B52: 15000 | C52: Fall | G52: Pruebas con pilotos y operadores reales
A53: Capacitación de usuarios | B53: 25000 | C53: Fall | G53: Pilotos, supervisores, administradores
A54: Soporte hypercare (1er mes) | B54: 30000 | C54: Post-Fall | G54: Equipo de guardia tras go-live
A55: COSTO TOTAL EXTRAS | B55: =SUM(B48:B54) -> 155000 | G55: Suma de costos adicionales
A58: RESUMEN FINANCIERO DEL PROYECTO
A59: Concepto | B59: Monto (Q) | C59: Duración | G59: Notas
A60: Fase Water | B60: =B15 -> 105500 | C60: =B14 -> 2 | G60: Cascada inicial: análisis y diseño
A61: Fase Scrum | B61: =B27 -> 493268.28 | C61: =B25 -> 10.551193 | G61: Desarrollo iterativo ágil
A62: Fase Fall | B62: =B41 -> 65400 | C62: =B40 -> 1.5 | G62: Cascada final: despliegue y cierre
A63: Costos Extra WSF | B63: =B55 -> 155000 | C63: — | G63: Docs formales, auditorías, capacitación
A64: COSTO TOTAL INTERNO DEL PROYECTO | B64: =SUM(B60:B63) -> 819168.28 | C64: =B14+B25+B40 -> 14.051193 | G64: Suma de las 3 fases + extras
A66: PRECIO AL CLIENTE (Contrato de Precio Fijo Cerrado)
A68: Margen objetivo (sobre venta) | B68: 0.45 | C68: % | G68: Mayor que ágil (35-45%) por riesgo de precio fijo
A69: PRECIO FIJO AL CLIENTE | B69: =B64/(1-B68) -> 1489396.9 | G69: Fórmula: costo total ÷ (1 − margen)
A71: Margen Bruto (Ganancia) | B71: =B69-B64 -> 670228.6 | G71: Fórmula: precio − Costo Total
A72: Markup % (margen sobre costo) | B72: =B71/B64 -> 0.81818182 | G72: Fórmula: margen bruto ÷ Costo Total

Sheet PMI
A1: ANÁLISIS FINANCIERO PMI — TransportesNova
A2: Reserva de Riesgos (EMV) · TMAR · ROI · ROA · Payback — Comparativa entre las 4 metodologías
A4: 1. PRESUPUESTO BASE POR METODOLOGÍA (vinculado de cada hoja)
A5: Concepto | B5: SCRUM | C5: KANBAN | D5: SCRUMBAN | E5: XP | F5: WSF | G5: Notas
A6: Costo Interno del Equipo | B6: =SCRUM!B24 -> 514250 | C6: =KANBAN!B25 -> 935000 | D6: =SCRUMBAN!B40 -> 423087.5 | E6: =XP!B32 -> 514250 | F6: ='Water Scrum Fall'!B15+'Water Scrum Fall'!B27+'Water Scrum Fall'!B41 -> 664168.28 | G6: Vinculado desde cada hoja de metodología
A7: Otros costos del proyecto (Sección 2) | B7: =B17 -> 35000 | C7: =B17 -> 35000 | D7: =B17 -> 35000 | E7: =B17 -> 35000 | F7: =B17+'Water Scrum Fall'!B55 -> 190000 | G7: Licencias, servidores, capacitación, etc.
A8: PRESUPUESTO BASE | B8: =B6+B7 -> 549250 | C8: =C6+C7 -> 970000 | D8: =D6+D7 -> 458087.5 | E8: =E6+E7 -> 549250 | F8: =F6+F7 -> 854168.28 | G8: Fórmula: Costo Interno + Otros costos
A10: 2. OTROS COSTOS DEL PROYECTO (común a todas las metodologías)
A11: Concepto | B11: Costo (Q) | G11: Justificación
A12: Licencias de software | B12: 8000 | G12: Herramientas Jira, GitHub, etc.
A13: Servidores y cloud | B13: 12000 | G13: AWS/Azure durante todo el proyecto
A14: Capacitación del equipo | B14: 5000 | G14: Onboarding y formación específica
A15: QA externo | B15: 6000 | G15: Auditoría de calidad puntual
A16: Documentación | B16: 4000 | G16: Manuales, diagramas, entregables
A17: TOTAL OTROS COSTOS | B17: =SUM(B12:B16) -> 35000 | G17: Mismo monto para las 4 metodologías
A19: 3. RESERVA DE RIESGOS — Valor Monetario Esperado (EMV) — PMBOK Gestión de Riesgos
A20: Fórmula EMV = Probabilidad × Impacto. Reserva de Riesgos = Σ EMV
A21: Riesgo identificado | B21: Probabilidad | C21: Impacto (Q) | D21: EMV (Q) | E21: Costo Mensual | F21: Tiempo | G21: Comentario
A22: Cambio de requerimientos del cliente | B22: 0.3 | C22: =E22*F22 -> 70125 | D22: =B22*C22 -> 21037.5 | E22: =Equipo!E13 -> 46750 | F22: 1.5 | G22: Alta probabilidad en proyectos ágiles
A23: Retraso técnico / curva de aprendizaje | B23: 0.25 | C23: =E23*F23 -> 23375 | D23: =B23*C23 -> 5843.75 | E23: =Equipo!E13 -> 46750 | F23: 0.5 | G23: Equipo junior incluido
A24: Disponibilidad de stakeholders | B24: 0.25 | C24: =E24*F24 -> 7012.5 | D24: =B24*C24 -> 1753.125 | E24: =Equipo!E13 -> 46750 | F24: 0.15 | G24: PO y SM a 50% FTE
A25: Defectos en producción | B25: 0.2 | C25: =E25*F25 -> 11687.5 | D25: =B25*C25 -> 2337.5 | E25: =Equipo!E13 -> 46750 | F25: 0.25 | G25: Mitigado en XP por pair programming
A26: Dependencias externas (cloud, API) | B26: 0.15 | C26: =E26*F26 -> 11687.5 | D26: =B26*C26 -> 1753.125 | E26: =Equipo!E13 -> 46750 | F26: 0.25 | G26: Servicios de terceros
A27: RESERVA DE RIESGOS TOTAL (Σ EMV) | D27: =SUM(D22:D26) -> 32725 | G27: Reserva común para las 4 metodologías
A29: 4. PRESUPUESTO INTERNO CON RIESGOS = Presupuesto Base + Reserva de Riesgos
A30: Concepto | B30: SCRUM | C30: KANBAN | D30: SCRUMBAN | E30: XP | F30: WSF | G30: Notas
A31: Presupuesto Base | B31: =B8 -> 549250 | C31: =C8 -> 970000 | D31: =D8 -> 458087.5 | E31: =E8 -> 549250 | F31: =F8 -> 854168.28
A32: (+) Reserva de Riesgos | B32: =D27 -> 32725 | C32: =D27 -> 32725 | D32: =D27 -> 32725 | E32: =D27 -> 32725 | F32: =D27 -> 32725
A33: PRESUPUESTO INTERNO CON RIESGOS | B33: =SUM(B31:B32) -> 581975 | C33: =SUM(C31:C32) -> 1002725 | D33: =SUM(D31:D32) -> 490812.5 | E33: =SUM(E31:E32) -> 581975 | F33: =SUM(F31:F32) -> 886893.28 | G33: Cost Baseline + Contingency Reserve (PMBOK)
A35: 5. PRECIO AL CLIENTE (Ingreso del Proyecto)
A36: Concepto | B36: SCRUM | C36: KANBAN | D36: SCRUMBAN | E36: XP | F36: WSF | G36: Notas
A37: Precio al Cliente (Ingreso Total) | B37: =SCRUM!B25 -> 1067925.8 | C37: =KANBAN!B24 -> 2400000 | D37: =SCRUMBAN!B39 -> 1057718.8 | E37: =XP!B27*XP!B19 -> 1320000 | F37: ='Water Scrum Fall'!B69 -> 1489396.9 | G37: Vinculado desde cada hoja
A39: 6. TMAR — Tasa Mínima Atractiva de Retorno (común a todas las metodologías)
A40: Fórmula: TMAR = Inflación + Riesgo + Rendimiento esperado
A41: Concepto | B41: Valor | G41: Justificación
A42: Inflación | B42: 0.05 | G42: Inflación esperada Guatemala (promedio)
A43: Riesgo del proyecto | B43: 0.08 | G43: Proyecto de complejidad normal
A44: Rendimiento esperado | B44: 0.25 | G44: Meta financiera de la empresa
A45: TMAR TOTAL | B45: =SUM(B42:B44) -> 0.38 | G45: Tasa mínima que el proyecto debe superar
A47: 7. BENEFICIOS ESPERADOS DEL SISTEMA (Ahorros anuales para TransportesNova)
A48: Beneficio | B48: Ahorro Anual (Q) | G48: Justificación
A49: Reducción de personal administrativo | B49: 240000 | G49: Automatización de gestión de flota y rutas (3p en 1p)
A50: Menos errores operativos | B50: 75000 | G50: Trazabilidad y validaciones del sistema
A51: Mayor productividad de pilotos | B51: 90000 | G51: Optimización de rutas y dashboards
A52: Menos tiempo en operaciones manuales | B52: 90000 | G52: Monitoreo en tiempo real y alertas
A53: BENEFICIO ANUAL TOTAL | B53: =SUM(B49:B52) -> 495000 | G53: Suma de ahorros anuales
A54: Beneficio Mensual | B54: =B53/12 -> 41250 | G54: Fórmula: Beneficio Anual ÷ 12
A56: 8. ROI — Retorno sobre la Inversión por Metodología
A57: Fórmula: ROI = (Beneficio Neto / Inversión) × 100 donde Beneficio Neto = Precio al Cliente − Inversión
A58: Concepto | B58: SCRUM | C58: KANBAN | D58: SCRUMBAN | E58: XP | F58: WSF | G58: Notas
A59: Inversión (Presupuesto Interno) | B59: =B33 -> 581975 | C59: =C33 -> 1002725 | D59: =D33 -> 490812.5 | E59: =E33 -> 581975 | F59: =F33 -> 886893.28
A60: Beneficio Esperado (Precio Cliente) | B60: =B37 -> 1067925.8 | C60: =C37 -> 2400000 | D60: =D37 -> 1057718.8 | E60: =E37 -> 1320000 | F60: =F37 -> 1489396.9
A61: Beneficio Neto | B61: =B60-B59 -> 485950.83 | C61: =C60-C59 -> 1397275 | D61: =D60-D59 -> 566906.25 | E61: =E60-E59 -> 738025 | F61: =F60-F59 -> 602503.6 | G61: Fórmula: Beneficio Esperado − Inversión
A62: ROI | B62: =B61/B59 -> 0.83500294 | C62: =C61/C59 -> 1.3934778 | D62: =D61/D59 -> 1.1550363 | E62: =E61/E59 -> 1.2681387 | F62: =F61/F59 -> 0.67934171 | G62: Retorno por cada Q1 invertido
A64: 9. ROI vs TMAR — ¿El proyecto es financieramente atractivo?
A65: Métrica | B65: SCRUM | C65: KANBAN | D65: SCRUMBAN | E65: XP | F65: WSF | G65: Decisión
A66: ROI | B66: =B62 -> 0.83500294 | C66: =C62 -> 1.3934778 | D66: =D62 -> 1.1550363 | E66: =E62 -> 1.2681387 | F66: =F62 -> 0.67934171
A67: TMAR | B67: =B45 -> 0.38 | C67: =B45 -> 0.38 | D67: =B45 -> 0.38 | E67: =B45 -> 0.38 | F67: =B45 -> 0.38
A68: Veredicto | B68: =IF(B62>B45,"VIABLE ✓","NO CONVIENE ✗") -> VIABLE ✓ | C68: =IF(C62>B45,"VIABLE ✓","NO CONVIENE ✗") -> VIABLE ✓ | D68: =IF(D62>B45,"VIABLE ✓","NO CONVIENE ✗") -> VIABLE ✓ | E68: =IF(E62>B45,"VIABLE ✓","NO CONVIENE ✗") -> VIABLE ✓ | F68: =IF(F62>B45,"VIABLE ✓","NO CONVIENE ✗") -> VIABLE ✓ | G68: ROI > TMAR = Aprobar proyecto
A70: 10. PAYBACK PERIOD — Tiempo de Recuperación de la Inversión
A71: Fórmula: Payback = Inversión / Beneficio Mensual
A72: Concepto | B72: SCRUM | C72: KANBAN | D72: SCRUMBAN | E72: XP | F72: WSF | G72: Notas
A73: Flujo Mensual | B73: =SCRUM!B4 -> 93500 | C73: =KANBAN!B12 -> 120000 | D73: =SCRUMBAN!B39/13 -> 81362.981 | E73: =XP!B27 -> 120000 | F73: ='Water Scrum Fall'!B69/15 -> 99293.125 | G73: Mismo para todas las metodologías
A74: Inversión | B74: =B59 -> 581975 | C74: =C59 -> 1002725 | D74: =D59 -> 490812.5 | E74: =E59 -> 581975 | F74: =F59 -> 886893.28
A75: Payback (meses) | B75: =B74/B73 -> 6.2243316 | C75: =C74/C73 -> 8.3560417 | D75: =D74/D73 -> 6.032381 | E75: =E74/E73 -> 4.8497917 | F75: =F74/F73 -> 8.9320714 | G75: Meses para recuperar la inversión
A77: 11. ROA — Retorno sobre Activos
A78: Fórmula: ROA = Utilidad Neta / Activos Totales
A79: Activo | B79: Valor (Q) | G79: Justificación
A80: Laptops del equipo | B80: 120000 | G80: 7 estaciones × ~Q17K
A81: Servidores y cloud | B81: 150000 | G81: Infraestructura técnica
A82: Licencias y software | B82: 30000 | G82: Herramientas de desarrollo
A83: Oficina e infraestructura | B83: 100000 | G83: Espacio y servicios físicos
A84: ACTIVOS TOTALES | B84: =SUM(B80:B83) -> 400000
A86: Concepto | B86: SCRUM | C86: KANBAN | D86: SCRUMBAN | E86: XP | F86: WSF | G86: Notas
A87: Utilidad Neta | B87: =B61 -> 485950.83 | C87: =C61 -> 1397275 | D87: =D61 -> 566906.25 | E87: =E61 -> 738025 | F87: =F61 -> 602503.6 | G87: Fórmula: Beneficio Esperado − Inversión
A88: Activos Totales | B88: =B84 -> 400000 | C88: =B84 -> 400000 | D88: =B84 -> 400000 | E88: =B84 -> 400000 | F88: =B84 -> 400000
A89: ROA | B89: =B87/B88 -> 1.2148771 | C89: =C87/C88 -> 3.4931875 | D89: =D87/D88 -> 1.4172656 | E89: =E87/E88 -> 1.8450625 | F89: =F87/F88 -> 1.506259 | G89: Retorno por cada Q1 invertido en activos
A91: 12. RESUMEN EJECUTIVO — Comparativa Final entre Metodologías
A92: Métrica PMI | B92: SCRUM | C92: KANBAN | D92: SCRUMBAN | E92: XP | F92: WSF | G92: Análisis
A93: Presupuesto Base | B93: =B8 -> 549250 | C93: =C8 -> 970000 | D93: =D8 -> 458087.5 | E93: =E8 -> 549250 | F93: =F8 -> 854168.28 | G93: Costo equipo + otros
A94: Reserva de Riesgos | B94: =D27 -> 32725 | C94: =D27 -> 32725 | D94: =D27 -> 32725 | E94: =D27 -> 32725 | F94: =D27 -> 32725 | G94: Igual para todas
A95: Presupuesto con Riesgos | B95: =B33 -> 581975 | C95: =C33 -> 1002725 | D95: =D33 -> 490812.5 | E95: =E33 -> 581975 | F95: =F33 -> 886893.28 | G95: Inversión total requerida
A96: Precio Cliente | B96: =B37 -> 1067925.8 | C96: =C37 -> 2400000 | D96: =D37 -> 1057718.8 | E96: =E37 -> 1320000 | F96: =F37 -> 1489396.9 | G96: Ingreso del proyecto
A97: Beneficio Neto | B97: =B61 -> 485950.83 | C97: =C61 -> 1397275 | D97: =D61 -> 566906.25 | E97: =E61 -> 738025 | F97: =F61 -> 602503.6 | G97: Utilidad por la entrega
A98: ROI | B98: =B62 -> 0.83500294 | C98: =C62 -> 1.3934778 | D98: =D62 -> 1.1550363 | E98: =E62 -> 1.2681387 | F98: =F62 -> 0.67934171 | G98: Retorno sobre inversión
A99: TMAR | B99: =B45 -> 0.38 | C99: =B45 -> 0.38 | D99: =B45 -> 0.38 | E99: =B45 -> 0.38 | F99: =B45 -> 0.38 | G99: Tasa mínima requerida

Sheet Equipo
A1: TransportesNova — Equipo de Trabajo (Supuestos Compartidos)
A3: Rol | B3: Descripción | C3: Salario Mensual (Q) | D3: FTE Asignado | E3: Costo Asignado (Q)
A4: PO | B4: Product Owner | C4: 22000 | D4: 0.5 | E4: =C4*D4 -> 11000
A5: SM/Facilitador | B5: Scrum Master / Facilitador | C5: 16500 | D5: 0.5 | E5: =C5*D5 -> 8250
A6: JN1 | B6: Junior Full Stack 1 | C6: 9000 | D6: 0.5 | E6: =C6*D6 -> 4500
A7: JN2 | B7: Junior Full Stack 2 | C7: 9000 | D7: 0.5 | E7: =C7*D7 -> 4500
A8: QA | B8: QA Engineer | C8: 7500 | D8: 0.5 | E8: =C8*D8 -> 3750
A9: SN1 | B9: Senior - DevOps | C9: 14000 | D9: 0.5 | E9: =C9*D9 -> 7000
A10: SN2 | B10: Senior - Cloud Engineer | C10: 15500 | D10: 0.5 | E10: =C10*D10 -> 7750
A12: COSTO TOTAL MENSUAL | E12: =SUM(C4:C10) -> 93500
A13: COSTO INTERNO (50% FTE – sin overhead) | E13: =SUM(E4:E10) -> 46750

Sheet Backlog
A1: Clave | B1: Título Historia | C1: Épica | D1: Descripción Épica | E1: Tipo | F1: SP | G1: Prioridad | H1: Estado
A2: EP01 — Usuarios, Roles y Permisos
A3: SCRUM-11 | B3: Registrar usuarios internos | C3: EP01 | D3: Usuarios, Roles y Permisos | E3: Historia | F3: 5 | G3: High | H3: Backlog
A4: SCRUM-12 | B4: Consultar listado de usuarios internos | C4: EP01 | D4: Usuarios, Roles y Permisos | E4: Historia | F4: 3 | G4: Medium | H4: Backlog
A5: SCRUM-13 | B5: Buscar usuarios por criterios | C5: EP01 | D5: Usuarios, Roles y Permisos | E5: Historia | F5: 3 | G5: Medium | H5: Backlog
A6: SCRUM-14 | B6: Editar información de usuarios | C6: EP01 | D6: Usuarios, Roles y Permisos | E6: Historia | F6: 5 | G6: Medium | H6: Backlog
A7: SCRUM-15 | B7: Inactivar usuarios internos | C7: EP01 | D7: Usuarios, Roles y Permisos | E7: Historia | F7: 3 | G7: Medium | H7: Backlog
A8: SCRUM-16 | B8: Asignar roles a usuarios | C8: EP01 | D8: Usuarios, Roles y Permisos | E8: Historia | F8: 5 | G8: High | H8: Backlog
A9: SCRUM-17 | B9: Restringir acceso según rol | C9: EP01 | D9: Usuarios, Roles y Permisos | E9: Historia | F9: 8 | G9: High | H9: Backlog
A10: SCRUM-18 | B10: Restablecer credenciales de acceso | C10: EP01 | D10: Usuarios, Roles y Permisos | E10: Historia | F10: 5 | G10: Medium | H10: Backlog
A11: SCRUM-19 | B11: Auditar cambios de usuarios y permisos | C11: EP01 | D11: Usuarios, Roles y Permisos | E11: Historia | F11: 8 | G11: Low | H11: Backlog
A12: Subtotal EP01 — 9 historias | F12: =SUM(F3:F11) -> 45
A14: EP02 — Gestión de Flota y Unidades
A15: SCRUM-20 | B15: Registrar unidades de transporte | C15: EP02 | D15: Gestión de Flota y Unidades | E15: Historia | F15: 5 | G15: High | H15: Backlog
A16: SCRUM-21 | B16: Consultar listado de unidades | C16: EP02 | D16: Gestión de Flota y Unidades | E16: Historia | F16: 3 | G16: Medium | H16: Backlog
A17: SCRUM-22 | B17: Buscar unidades por placa o tipo | C17: EP02 | D17: Gestión de Flota y Unidades | E17: Historia | F17: 3 | G17: Medium | H17: Backlog
A18: SCRUM-23 | B18: Editar información de unidades | C18: EP02 | D18: Gestión de Flota y Unidades | E18: Historia | F18: 5 | G18: Medium | H18: Backlog
A19: SCRUM-24 | B19: Cambiar estado operativo de una unidad | C19: EP02 | D19: Gestión de Flota y Unidades | E19: Historia | F19: 5 | G19: High | H19: Backlog
A20: SCRUM-25 | B20: Consultar detalle de una unidad | C20: EP02 | D20: Gestión de Flota y Unidades | E20: Historia | F20: 3 | G20: Medium | H20: Backlog
A21: SCRUM-26 | B21: Validar disponibilidad antes de asignar unidad | C21: EP02 | D21: Gestión de Flota y Unidades | E21: Historia | F21: 8 | G21: High | H21: Backlog
A22: SCRUM-27 | B22: Registrar capacidad y tipo de carga soportada | C22: EP02 | D22: Gestión de Flota y Unidades | E22: Historia | F22: 5 | G22: High | H22: Backlog
A23: SCRUM-28 | B23: Consultar historial de uso por unidad | C23: EP02 | D23: Gestión de Flota y Unidades | E23: Historia | F23: 8 | G23: Medium | H23: Backlog
A24: SCRUM-29 | B24: Dar de baja una unidad | C24: EP02 | D24: Gestión de Flota y Unidades | E24: Historia | F24: 5 | G24: Low | H24: Backlog
A25: SCRUM-30 | B25: Registrar documentación legal de una unidad | C25: EP02 | D25: Gestión de Flota y Unidades | E25: Historia | F25: 5 | G25: High | H25: Backlog
A26: SCRUM-31 | B26: Alertar vencimiento de documentos de unidad | C26: EP02 | D26: Gestión de Flota y Unidades | E26: Historia | F26: 5 | G26: Medium | H26: Backlog
A27: Subtotal EP02 — 12 historias | F27: =SUM(F15:F26) -> 60
A29: EP03 — Gestión de Pilotos
A30: SCRUM-32 | B30: Registrar pilotos | C30: EP03 | D30: Gestión de Pilotos | E30: Historia | F30: 5 | G30: High | H30: Backlog
A31: SCRUM-33 | B31: Consultar listado de pilotos | C31: EP03 | D31: Gestión de Pilotos | E31: Historia | F31: 3 | G31: Medium | H31: Backlog
A32: SCRUM-34 | B32: Actualizar información de pilotos | C32: EP03 | D32: Gestión de Pilotos | E32: Historia | F32: 5 | G32: Medium | H32: Backlog
A33: SCRUM-35 | B33: Registrar disponibilidad de pilotos | C33: EP03 | D33: Gestión de Pilotos | E33: Historia | F33: 5 | G33: High | H33: Backlog
A34: SCRUM-36 | B34: Validar licencia y vencimiento | C34: EP03 | D34: Gestión de Pilotos | E34: Historia | F34: 8 | G34: High | H34: Backlog
A35: SCRUM-37 | B35: Impedir doble asignación de piloto | C35: EP03 | D35: Gestión de Pilotos | E35: Historia | F35: 8 | G35: High | H35: Backlog
A36: SCRUM-38 | B36: Consultar historial operativo del piloto | C36: EP03 | D36: Gestión de Pilotos | E36: Historia | F36: 8 | G36: Medium | H36: Backlog
A37: SCRUM-39 | B37: Inactivar pilotos | C37: EP03 | D37: Gestión de Pilotos | E37: Historia | F37: 3 | G37: Medium | H37: Backlog
A38: SCRUM-40 | B38: Registrar observaciones de desempeño | C38: EP03 | D38: Gestión de Pilotos | E38: Historia | F38: 5 | G38: Medium | H38: Backlog
A39: SCRUM-41 | B39: Registrar documentación personal del piloto | C39: EP03 | D39: Gestión de Pilotos | E39: Historia | F39: 5 | G39: Medium | H39: Backlog
A40: SCRUM-42 | B40: Alertar vencimiento de licencia del piloto | C40: EP03 | D40: Gestión de Pilotos | E40: Historia | F40: 5 | G40: High | H40: Backlog
A41: Subtotal EP03 — 11 historias | F41: =SUM(F30:F40) -> 60
A43: EP04 — Rutas y Planificación Operativa
A44: SCRUM-43 | B44: Registrar rutas | C44: EP04 | D44: Rutas y Planificación Operativa | E44: Historia | F44: 5 | G44: High | H44: Backlog
A45: SCRUM-44 | B45: Consultar rutas registradas | C45: EP04 | D45: Rutas y Planificación Operativa | E45: Historia | F45: 3 | G45: Medium | H45: Backlog
A46: SCRUM-45 | B46: Editar rutas existentes | C46: EP04 | D46: Rutas y Planificación Operativa | E46: Historia | F46: 5 | G46: Medium | H46: Backlog
A47: SCRUM-46 | B47: Programar horarios de salida y llegada | C47: EP04 | D47: Rutas y Planificación Operativa | E47: Historia | F47: 5 | G47: High | H47: Backlog
A48: SCRUM-47 | B48: Asignar unidad a una ruta | C48: EP04 | D48: Rutas y Planificación Operativa | E48: Historia | F48: 5 | G48: High | H48: Backlog
A49: SCRUM-48 | B49: Asignar piloto a una ruta | C49: EP04 | D49: Rutas y Planificación Operativa | E49: Historia | F49: 5 | G49: High | H49: Backlog
A50: SCRUM-49 | B50: Validar coherencia de asignaciones de ruta | C50: EP04 | D50: Rutas y Planificación Operativa | E50: Historia | F50: 8 | G50: High | H50: Backlog
A51: SCRUM-50 | B51: Reprogramar rutas ante contingencias | C51: EP04 | D51: Rutas y Planificación Operativa | E51: Historia | F51: 8 | G51: High | H51: Backlog
A52: SCRUM-51 | B52: Aprobar cambios críticos de ruta | C52: EP04 | D52: Rutas y Planificación Operativa | E52: Historia | F52: 5 | G52: Medium | H52: Backlog
A53: SCRUM-52 | B53: Consultar calendario operativo de rutas | C53: EP04 | D53: Rutas y Planificación Operativa | E53: Historia | F53: 8 | G53: Medium | H53: Backlog
A54: SCRUM-53 | B54: Consultar rutas alternativas disponibles | C54: EP04 | D54: Rutas y Planificación Operativa | E54: Historia | F54: 5 | G54: Low | H54: Backlog
A55: SCRUM-54 | B55: Comparar rutas por distancia estimada | C55: EP04 | D55: Rutas y Planificación Operativa | E55: Historia | F55: 5 | G55: Low | H55: Backlog
... A58: SCRUM-57 | B58: Confirmar ruta sugerida como ruta operativa | C58: EP04 | D58: Rutas y Planificación Operativa | E58: Historia | F58: 5 | G58: Low | H58: Backlog
A59: Subtotal EP04 — 15 historias | F59: =SUM(F44:F58) -> 85
A61: EP05 — Monitoreo en Tiempo Real
A62: SCRUM-58 | B62: Mostrar unidades activas en mapa | C62: EP05 | D62: Monitoreo en Tiempo Real | E62: Historia | F62: 8 | G62: Medium | H62: Backlog
A63: SCRUM-59 | B63: Diferenciar unidades por estado operativo | C63: EP05 | D63: Monitoreo en Tiempo Real | E63: Historia | F63: 5 | G63: Medium | H63: Backlog
A64: SCRUM-60 | B64: Actualizar ubicación de unidades en intervalos definidos | C64: EP05 | D64: Monitoreo en Tiempo Real | E64: Historia | F64: 8 | G64: Medium | H64: Backlog
A65: SCRUM-61 | B65: Consultar estado actual de una unidad en ruta | C65: EP05 | D65: Monitoreo en Tiempo Real | E65: Historia | F65: 5 | G65: Medium | H65: Backlog
A66: SCRUM-62 | B66: Visualizar progreso de viaje por ruta | C66: EP05 | D66: Monitoreo en Tiempo Real | E66: Historia | F66: 8 | G66: Medium | H66: Backlog
A67: SCRUM-63 | B67: Identificar unidades retrasadas | C67: EP05 | D67: Monitoreo en Tiempo Real | E67: Historia | F67: 5 | G67: High | H67: Backlog
A68: SCRUM-64 | B68: Identificar desvíos de ruta | C68: EP05 | D68: Monitoreo en Tiempo Real | E68: Historia | F68: 8 | G68: High | H68: Backlog
A69: SCRUM-65 | B69: Consultar detalle en vivo de una unidad | C69: EP05 | D69: Monitoreo en Tiempo Real | E69: Historia | F69: 5 | G69: Medium | H69: Backlog
A70: SCRUM-66 | B70: Filtrar monitoreo por región o estado | C70: EP05 | D70: Monitoreo en Tiempo Real | E70: Historia | F70: 5 | G70: Medium | H70: Backlog
A71: SCRUM-67 | B71: Registrar pérdida temporal de señal | C71: EP05 | D71: Monitoreo en Tiempo Real | E71: Historia | F71: 8 | G71: Medium | H71: Backlog
A72: SCRUM-68 | B72: Mostrar última ubicación conocida de una unidad | C72: EP05 | D72: Monitoreo en Tiempo Real | E72: Historia | F72: 5 | G72: Medium | H72: Backlog
A73: Subtotal EP05 — 11 historias | F73: =SUM(F62:F72) -> 70
A75: EP06 — Gestión de Incidencias
A76: SCRUM-69 | B76: Registrar incidencias en ruta | C76: EP06 | D76: Gestión de Incidencias | E76: Historia | F76: 5 | G76: High | H76: Backlog
A77: SCRUM-70 | B77: Clasificar tipo de incidencia | C77: EP06 | D77: Gestión de Incidencias | E77: Historia | F77: 3 | G77: High | H77: Backlog
A78: SCRUM-71 | B78: Asignar prioridad a incidencias | C78: EP06 | D78: Gestión de Incidencias | E78: Historia | F78: 3 | G78: High | H78: Backlog
A79: SCRUM-72 | B79: Dar seguimiento al estado de una incidencia | C79: EP06 | D79: Gestión de Incidencias | E79: Historia | F79: 5 | G79: High | H79: Backlog
A80: SCRUM-73 | B80: Consultar historial de incidencias | C80: EP06 | D80: Gestión de Incidencias | E80: Historia | F80: 8 | G80: Medium | H80: Backlog
A81: SCRUM-74 | B81: Adjuntar evidencia a incidencias | C81: EP06 | D81: Gestión de Incidencias | E81: Historia | F81: 5 | G81: Medium | H81: Backlog
A82: SCRUM-75 | B82: Escalar incidencias críticas | C82: EP06 | D82: Gestión de Incidencias | E82: Historia | F82: 8 | G82: High | H82: Backlog
A83: SCRUM-76 | B83: Cerrar incidencias con resolución documentada | C83: EP06 | D83: Gestión de Incidencias | E83: Historia | F83: 5 | G83: High | H83: Backlog
A84: SCRUM-77 | B84: Asignar responsable de atención a una incidencia | C84: EP06 | D84: Gestión de Incidencias | E84: Historia | F84: 5 | G84: High | H84: Backlog
A85: SCRUM-78 | B85: Registrar comentarios de seguimiento de incidencia | C85: EP06 | D85: Gestión de Incidencias | E85: Historia | F85: 3 | G85: Medium | H85: Backlog
A86: Subtotal EP06 — 10 historias | F86: =SUM(F76:F85) -> 50
A88: EP07 — Mantenimiento Preventivo y Correctivo
A89: SCRUM-79 | B89: Registrar mantenimientos preventivos | C89: EP07 | D89: Mantenimiento Preventivo y Correctivo | E89: Historia | F89: 5 | G89: Medium | H89: Backlog
A90: SCRUM-80 | B90: Registrar mantenimientos correctivos | C90: EP07 | D90: Mantenimiento Preventivo y Correctivo | E90: Historia | F90: 5 | G90: Medium | H90: Backlog
A91: SCRUM-81 | B91: Consultar calendario de mantenimiento | C91: EP07 | D91: Mantenimiento Preventivo y Correctivo | E91: Historia | F91: 8 | G91: Medium | H91: Backlog
A92: SCRUM-82 | B92: Bloquear unidades con mantenimiento vencido | C92: EP07 | D92: Mantenimiento Preventivo y Correctivo | E92: Historia | F92: 8 | G92: High | H92: Backlog
A93: SCRUM-83 | B93: Registrar costos de mantenimiento | C93: EP07 | D93: Mantenimiento Preventivo y Correctivo | E93: Historia | F93: 5 | G93: Medium | H93: Backlog
A94: SCRUM-84 | B94: Consultar historial de mantenimiento por unidad | C94: EP07 | D94: Mantenimiento Preventivo y Correctivo | E94: Historia | F94: 8 | G94: Medium | H94: Backlog
A95: SCRUM-85 | B95: Registrar taller y responsable | C95: EP07 | D95: Mantenimiento Preventivo y Correctivo | E95: Historia | F95: 3 | G95: Medium | H95: Backlog
A96: SCRUM-86 | B96: Actualizar estado de unidad después de mantenimiento | C96: EP07 | D96: Mantenimiento Preventivo y Correctivo | E96: Historia | F96: 5 | G96: High | H96: Backlog
A97: SCRUM-87 | B97: Registrar observaciones técnicas de mantenimiento | C97: EP07 | D97: Mantenimiento Preventivo y Correctivo | E97: Historia | F97: 3 | G97: Low | H97: Backlog
A98: SCRUM-88 | B98: Consultar unidades próximas a mantenimiento | C98: EP07 | D98: Mantenimiento Preventivo y Correctivo | E98: Historia | F98: 5 | G98: Medium | H98: Backlog
A99: SCRUM-89 | B99: Programar mantenimiento preventivo por kilometraje o fecha | C99: EP07 | D99: Mantenimiento Preventivo y Correctivo | E99: Historia | F99: 8 | G99: Medium | H99: Backlog
A100: Subtotal EP07 — 11 historias | F100: =SUM(F89:F99) -> 63
A102: EP08 — Alertas y Notificaciones
A103: SCRUM-90 | B103: Generar alerta por retraso de unidad | C103: EP08 | D103: Alertas y Notificaciones | E103: Historia | F103: 5 | G103: High | H103: Backlog
A104: SCRUM-91 | B104: Generar alerta por desvío de ruta | C104: EP08 | D104: Alertas y Notificaciones | E104: Historia | F104: 8 | G104: High | H104: Backlog
A105: SCRUM-92 | B105: Generar alerta por mantenimiento próximo | C105: EP08 | D105: Alertas y Notificaciones | E105: Historia | F105: 5 | G105: Medium | H105: Backlog
A106: SCRUM-93 | B106: Visualizar bandeja de alertas activas | C106: EP08 | D106: Alertas y Notificaciones | E106: Historia | F106: 5 | G106: Medium | H106: Backlog
A107: SCRUM-94 | B107: Marcar alertas como atendidas | C107: EP08 | D107: Alertas y Notificaciones | E107: Historia | F107: 3 | G107: Medium | H107: Backlog
A108: SCRUM-95 | B108: Crear regla de alerta por retraso | C108: EP08 | D108: Alertas y Notificaciones | E108: Historia | F108: 5 | G108: Low | H108: Backlog
A109: SCRUM-96 | B109: Crear regla de alerta por desvío | C109: EP08 | D109: Alertas y Notificaciones | E109: Historia | F109: 5 | G109: Low | H109: Backlog
...

Sheet MVP
A1: Clave | B1: Título Historia | C1: Épica | D1: Descripción Épica | E1: Tipo | F1: SP | G1: Prioridad | H1: Estado
A2: EP01 — Usuarios, Roles y Permisos
A3: SCRUM-11 | B3: Registrar usuarios internos | C3: EP01 | D3: Usuarios, Roles y Permisos | E3: Historia | F3: 5 | G3: High | H3: Backlog
A4: SCRUM-16 | B4: Asignar roles a usuarios | C4: EP01 | D4: Usuarios, Roles y Permisos | E4: Historia | F4: 5 | G4: High | H4: Backlog
A5: SCRUM-17 | B5: Restringir acceso según rol | C5: EP01 | D5: Usuarios, Roles y Permisos | E5: Historia | F5: 8 | G5: High | H5: Backlog
A6: Subtotal EP01 — 3 historias | F6: =SUM(F3:F5) -> 18
A8: EP02 — Gestión de Flota y Unidades
A9: SCRUM-20 | B9: Registrar unidades de transporte | C9: EP02 | D9: Gestión de Flota y Unidades | E9: Historia | F9: 5 | G9: High | H9: Backlog
A10: SCRUM-21 | B10: Consultar listado de unidades | C10: EP02 | D10: Gestión de Flota y Unidades | E10: Historia | F10: 3 | G10: Medium | H10: Backlog
A11: SCRUM-24 | B11: Cambiar estado operativo de una unidad | C11: EP02 | D11: Gestión de Flota y Unidades | E11: Historia | F11: 5 | G11: High | H11: Backlog
A12: SCRUM-26 | B12: Validar disponibilidad antes de asignar unidad | C12: EP02 | D12: Gestión de Flota y Unidades | E12: Historia | F12: 8 | G12: High | H12: Backlog
A13: SCRUM-27 | B13: Registrar capacidad y tipo de carga soportada | C13: EP02 | D13: Gestión de Flota y Unidades | E13: Historia | F13: 5 | G13: High | H13: Backlog
A14: Subtotal EP02 — 5 historias | F14: =SUM(F9:F13) -> 26
A16: EP03 — Gestión de Pilotos
A17: SCRUM-32 | B17: Registrar pilotos | C17: EP03 | D17: Gestión de Pilotos | E17: Historia | F17: 5 | G17: High | H17: Backlog
A18: SCRUM-33 | B18: Consultar listado de pilotos | C18: EP03 | D18: Gestión de Pilotos | E18: Historia | F18: 3 | G18: Medium | H18: Backlog
A19: SCRUM-35 | B19: Registrar disponibilidad de pilotos | C19: EP03 | D19: Gestión de Pilotos | E19: Historia | F19: 5 | G19: High | H19: Backlog
A20: SCRUM-36 | B20: Validar licencia y vencimiento | C20: EP03 | D20: Gestión de Pilotos | E20: Historia | F20: 8 | G20: High | H20: Backlog
A21: SCRUM-37 | B21: Impedir doble asignación de piloto | C21: EP03 | D21: Gestión de Pilotos | E21: Historia | F21: 8 | G21: High | H21: Backlog
A22: Subtotal EP03 — 5 historias | F22: =SUM(F17:F21) -> 29
A24: EP04 — Rutas y Planificación Operativa
A25: SCRUM-43 | B25: Registrar rutas | C25: EP04 | D25: Rutas y Planificación Operativa | E25: Historia | F25: 5 | G25: High | H25: Backlog
A26: SCRUM-44 | B26: Consultar rutas registradas | C26: EP04 | D26: Rutas y Planificación Operativa | E26: Historia | F26: 3 | G26: Medium | H26: Backlog
A27: SCRUM-46 | B27: Programar horarios de salida y llegada | C27: EP04 | D27: Rutas y Planificación Operativa | E27: Historia | F27: 5 | G27: High | H27: Backlog
A28: SCRUM-47 | B28: Asignar unidad a una ruta | C28: EP04 | D28: Rutas y Planificación Operativa | E28: Historia | F28: 5 | G28: High | H28: Backlog
A29: SCRUM-48 | B29: Asignar piloto a una ruta | C29: EP04 | D29: Rutas y Planificación Operativa | E29: Historia | F29: 5 | G29: High | H29: Backlog
A30: SCRUM-49 | B30: Validar coherencia de asignaciones de ruta | C30: EP04 | D30: Rutas y Planificación Operativa | E30: Historia | F30: 8 | G30: High | H30: Backlog
A31: SCRUM-52 | B31: Consultar calendario operativo de rutas | C31: EP04 | D31: Rutas y Planificación Operativa | E31: Historia | F31: 8 | G31: Medium | H31: Backlog
A32: Subtotal EP04 — 7 historias | F32: =SUM(F25:F31) -> 39
A34: EP06 — Gestión de Incidencias
A35: SCRUM-69 | B35: Registrar incidencias en ruta | C35: EP06 | D35: Gestión de Incidencias | E35: Historia | F35: 5 | G35: High | H35: Backlog
A36: SCRUM-70 | B36: Clasificar tipo de incidencia | C36: EP06 | D36: Gestión de Incidencias | E36: Historia | F36: 3 | G36: High | H36: Backlog
A37: SCRUM-71 | B37: Asignar prioridad a incidencias | C37: EP06 | D37: Gestión de Incidencias | E37: Historia | F37: 3 | G37: High | H37: Backlog
A38: SCRUM-72 | B38: Dar seguimiento al estado de una incidencia | C38: EP06 | D38: Gestión de Incidencias | E38: Historia | F38: 5 | G38: High | H38: Backlog
A39: SCRUM-75 | B39: Escalar incidencias críticas | C39: EP06 | D39: Gestión de Incidencias | E39: Historia | F39: 8 | G39: High | H39: Backlog
A40: SCRUM-76 | B40: Cerrar incidencias con resolución documentada | C40: EP06 | D40: Gestión de Incidencias | E40: Historia | F40: 5 | G40: High | H40: Backlog
A41: Subtotal EP06 — 6 historias | F41: =SUM(F35:F40) -> 29
A43: EP09 — Dashboard Ejecutivo y Reportes
A44: SCRUM-102 | B44: Visualizar indicadores generales en dashboard | C44: EP09 | D44: Dashboard Ejecutivo y Reportes | E44: Historia | F44: 8 | G44: High | H44: Backlog
A45: SCRUM-103 | B45: Mostrar total de unidades activas | C45: EP09 | D45: Dashboard Ejecutivo y Reportes | E45: Historia | F45: 3 | G45: High | H45: Backlog
A46: SCRUM-104 | B46: Mostrar total de rutas programadas | C46: EP09 | D46: Dashboard Ejecutivo y Reportes | E46: Historia | F46: 3 | G46: High | H46: Backlog
A47: SCRUM-105 | B47: Mostrar incidencias abiertas | C47: EP09 | D47: Dashboard Ejecutivo y Reportes | E47: Historia | F47: 3 | G47: High | H47: Backlog
A48: SCRUM-106 | B48: Mostrar unidades disponibles y no disponibles | C48: EP09 | D48: Dashboard Ejecutivo y Reportes | E48: Historia | F48: 3 | G48: High | H48: Backlog
A49: SCRUM-111 | B49: Consultar disponibilidad de flota | C49: EP09 | D49: Dashboard Ejecutivo y Reportes | E49: Historia | F49: 5 | G49: High | H49: Backlog
A50: Subtotal EP09 — 6 historias | F50: =SUM(F44:F49) -> 25
A52: EP10 — Trazabilidad Interna de Encomiendas
A53: SCRUM-116 | B53: Registrar encomiendas | C53: EP10 | D53: Trazabilidad Interna de Encomiendas | E53: Historia | F53: 5 | G53: High | H53: Backlog
A54: SCRUM-117 | B54: Clasificar encomiendas por tipo y tamaño | C54: EP10 | D54: Trazabilidad Interna de Encomiendas | E54: Historia | F54: 5 | G54: High | H54: Backlog
A55: SCRUM-118 | B55: Asignar encomiendas a rutas | C55: EP10 | D55: Trazabilidad Interna de Encomiendas | E55: Historia | F55: 5 | G55: High | H55: Backlog
A56: SCRUM-119 | B56: Asignar encomiendas a unidades | C56: EP10 | D56: Trazabilidad Interna de Encomiendas | E56: Historia | F56: 5 | G56: High | H56: Backlog
A57: SCRUM-120 | B57: Actualizar estado interno de encomienda | C57: EP10 | D57: Trazabilidad Interna de Encomiendas | E57: Historia | F57: 5 | G57: High | H57: Backlog
A58: SCRUM-121 | B58: Consultar estado interno de una encomienda | C58: EP10 | D58: Trazabilidad Interna de Encomiendas | E58: Historia | F58: 3 | G58: High | H58: Backlog
A59: SCRUM-123 | B59: Registrar recepción de encomienda en punto de origen | C59: EP10 | D59: Trazabilidad Interna de Encomiendas | E59: Historia | F59: 5 | G59: High | H59: Backlog
A60: SCRUM-124 | B60: Registrar entrega de encomienda en punto de destino | C60: EP10 | D60: Trazabilidad Interna de Encomiendas | E60: Historia | F60: 5 | G60: High | H60: Backlog
A61: SCRUM-125 | B61: Marcar encomienda como pendiente, en tránsito, entregada o con incidencia | C61: EP10 | D61: Trazabilidad Interna de Encomiendas | E61: Historia | F61: 5 | G61: High | H61: Backlog
A62: Subtotal EP10 — 9 historias | F62: =SUM(F53:F61) -> 43
A64: Total MVP — 41 historias | F64: =SUM(F6+F14+F22+F32+F41+F50+F62) -> 209
